{
    "dev": {
        "awscloudformation": {
            "AuthRoleName": "amplify-boyaki-dev-233804-authRole",
            "UnauthRoleArn": "arn:aws:iam::933345684592:role/amplify-boyaki-dev-233804-unauthRole",
            "AuthRoleArn": "arn:aws:iam::933345684592:role/amplify-boyaki-dev-233804-authRole",
            "Region": "ap-northeast-1",
            "DeploymentBucketName": "amplify-boyaki-dev-233804-deployment",
            "UnauthRoleName": "amplify-boyaki-dev-233804-unauthRole",
            "StackName": "amplify-boyaki-dev-233804",
            "StackId": "arn:aws:cloudformation:ap-northeast-1:933345684592:stack/amplify-boyaki-dev-233804/e6099340-099f-11ec-af4c-0e9cfcf32e9f",
            "AmplifyAppId": "d3891b3dyuexe0"
        },
        "categories": {
            "auth": {
                "boyakia8aded0d": {}
            },
            "hosting": {
                "amplifyhosting": {
                    "appId": "d3891b3dyuexe0",
                    "type": "manual"
                }
            }
        }
    }
}